music/__init__.py
music/constants.py
music/elements.py
music/track.py
python_music-0.0.2.dist-info/LICENSE
python_music-0.0.2.dist-info/METADATA
python_music-0.0.2.dist-info/WHEEL
python_music-0.0.2.dist-info/top_level.txt
python_music-0.0.2.dist-info/RECORD
